galo_ioc/__init__.py
galo_ioc-0.15.0.dist-info/LICENSE
galo_ioc-0.15.0.dist-info/WHEEL
galo_ioc-0.15.0.dist-info/METADATA
galo_ioc-0.15.0.dist-info/RECORD
