Metadata-Version: 2.1
Name: galo_ioc
Version: 0.15.0
Summary: Provides an implementation of the service locator pattern.
Author-email: Maxim Sakhno <maxim.sakhno@gmail.com>
Requires-Python: >=3.8
Classifier: Development Status :: 4 - Beta
Classifier: License :: OSI Approved :: MIT License
Classifier: Programming Language :: Python
Classifier: Programming Language :: Python :: 3
Classifier: Programming Language :: Python :: 3 :: Only
Classifier: Programming Language :: Python :: 3.8
Classifier: Programming Language :: Python :: 3.9
Classifier: Programming Language :: Python :: 3.10
Classifier: Operating System :: OS Independent
Classifier: Intended Audience :: Information Technology
Classifier: Intended Audience :: Developers
Classifier: Topic :: Software Development
Classifier: Topic :: Software Development :: Libraries
Classifier: Topic :: Software Development :: Libraries :: Python Modules
Classifier: Typing :: Typed
Requires-Dist: mypy==0.931 ; extra == "dev"
Requires-Dist: flake8==4.0.1 ; extra == "dev"
Requires-Dist: flake8-quotes==3.3.1 ; extra == "dev"
Requires-Dist: black==21.12b0 ; extra == "dev"
Requires-Dist: isort==5.10.1 ; extra == "dev"
Requires-Dist: bandit==1.7.1 ; extra == "dev"
Requires-Dist: pytest==6.2.5 ; extra == "test"
Requires-Dist: pytest-cov==3.0.0 ; extra == "test"
Requires-Dist: pytest-asyncio==0.17.0 ; extra == "test"
Project-URL: Source, https://github.com/maximsakhno/galo-ioc
Provides-Extra: dev
Provides-Extra: test
